eseries/__init__.py
eseries/__main__.py
eseries/cli.py
eseries/eng.py
eseries/eseries.py
eseries/version.py
eseries-1.2.1.dist-info/LICENSE.txt
eseries-1.2.1.dist-info/METADATA
eseries-1.2.1.dist-info/WHEEL
eseries-1.2.1.dist-info/entry_points.txt
eseries-1.2.1.dist-info/top_level.txt
eseries-1.2.1.dist-info/RECORD
