Metadata-Version: 2.1
Name: eseries
Version: 1.2.1
Summary: Working with the E-series of preferred numbers used for electronic components, such as resistors and capacitors
Home-page: https://github.com/rob-smallshire/eseries
Author: Sixty North AS
Author-email: rob@sixty-north.com
License: MIT License
Keywords: electronics resistors capacitors preferred-numbers
Platform: UNKNOWN
Classifier: Development Status :: 5 - Production/Stable
Classifier: Intended Audience :: Developers
Classifier: Topic :: Scientific/Engineering
Classifier: Topic :: Software Development :: Libraries
Classifier: License :: OSI Approved :: MIT License
Classifier: Programming Language :: Python :: 2.7
Classifier: Programming Language :: Python :: 3
Classifier: Programming Language :: Python :: 3.4
Classifier: Programming Language :: Python :: 3.5
Classifier: Programming Language :: Python :: 3.6
Classifier: Programming Language :: Python :: 3.7
Classifier: Programming Language :: Python :: 3.8
Classifier: Programming Language :: Python :: 3.9
Provides-Extra: dev
Provides-Extra: doc
Provides-Extra: test
